server.py
mseep_academic_search-0.1.4.dist-info/licenses/LICENSE
mseep_academic_search-0.1.4.dist-info/METADATA
mseep_academic_search-0.1.4.dist-info/WHEEL
mseep_academic_search-0.1.4.dist-info/entry_points.txt
mseep_academic_search-0.1.4.dist-info/top_level.txt
mseep_academic_search-0.1.4.dist-info/RECORD
